eigensheep/__init__.py
eigensheep/core.py
eigensheep/template.py
eigensheep/test.py
eigensheep-1.0.0.dist-info/LICENSE
eigensheep-1.0.0.dist-info/METADATA
eigensheep-1.0.0.dist-info/WHEEL
eigensheep-1.0.0.dist-info/top_level.txt
eigensheep-1.0.0.dist-info/RECORD
