Metadata-Version: 2.1
Name: eigensheep
Version: 1.0.0
Summary: Run Jupyter cells in AWS Lambda for massively parallel experimentation
Home-page: https://github.com/antimatter15/eigensheep
Author: Kevin Kwok
Author-email: antimatter15@gmail.com
License: UNKNOWN
Platform: UNKNOWN
Classifier: Programming Language :: Python :: 3
Classifier: Programming Language :: Python :: 2
Classifier: License :: OSI Approved :: MIT License
Classifier: Operating System :: OS Independent
Classifier: Development Status :: 3 - Alpha
Classifier: Framework :: Jupyter
Classifier: Topic :: Scientific/Engineering
Classifier: Intended Audience :: Science/Research
Classifier: Intended Audience :: Developers
Requires-Dist: tqdm
Requires-Dist: boto3
Requires-Dist: ipython
Requires-Dist: ipywidgets
Requires-Dist: futures ; python_version == "2.7"
